wake.py
wake_cli-1.0.0.dist-info/entry_points.txt
wake_cli-1.0.0.dist-info/WHEEL
wake_cli-1.0.0.dist-info/METADATA
wake_cli-1.0.0.dist-info/RECORD
